SuperLang/__init__.py
SuperLang/data.py
SuperLang/error.py
SuperLang/interpreter.py
SuperLang/lexer.py
SuperLang/parse.py
SuperLang/runner.py
SuperLang/tokens.py
shadowlang-0.1.0.dist-info/METADATA
shadowlang-0.1.0.dist-info/WHEEL
shadowlang-0.1.0.dist-info/entry_points.txt
shadowlang-0.1.0.dist-info/top_level.txt
shadowlang-0.1.0.dist-info/RECORD
